skilleter_thingy/__init__.py
skilleter_thingy/addpath.py
skilleter_thingy/console_colours.py
skilleter_thingy/ffind.py
skilleter_thingy/ggit.py
skilleter_thingy/ggrep.py
skilleter_thingy/git_br.py
skilleter_thingy/git_ca.py
skilleter_thingy/git_cleanup.py
skilleter_thingy/git_co.py
skilleter_thingy/git_common.py
skilleter_thingy/git_hold.py
skilleter_thingy/git_parent.py
skilleter_thingy/git_retag.py
skilleter_thingy/git_review.py
skilleter_thingy/git_update.py
skilleter_thingy/git_wt.py
skilleter_thingy/gitcmp_helper.py
skilleter_thingy/gitprompt.py
skilleter_thingy/linecount.py
skilleter_thingy/multigit.py
skilleter_thingy/py_audit.py
skilleter_thingy/remdir.py
skilleter_thingy/rpylint.py
skilleter_thingy/test.py
skilleter_thingy/tfparse.py
skilleter_thingy/trimpath.py
skilleter_thingy/venv_create.py
skilleter_thingy/venv_template.py
skilleter_thingy/xchmod.py
skilleter_thingy/yamlcheck.py
skilleter_thingy-0.3.25.dist-info/licenses/LICENSE
skilleter_thingy-0.3.25.dist-info/METADATA
skilleter_thingy-0.3.25.dist-info/WHEEL
skilleter_thingy-0.3.25.dist-info/entry_points.txt
skilleter_thingy-0.3.25.dist-info/top_level.txt
skilleter_thingy-0.3.25.dist-info/RECORD
