Metadata-Version: 2.4
Name: skilleter_thingy
Version: 0.3.25
Summary: A collection of useful utilities, mainly aimed at making Git more friendly
Author-email: John Skilleter <john@skilleter.org.uk>
Project-URL: Home, https://skilleter.org.uk
Project-URL: Repository, https://gitlab.com/skilleter/skilleter-thingy
Project-URL: Issues, https://gitlab.com/skilleter/skilleter-thingy/-/issues
Classifier: Programming Language :: Python :: 3
Classifier: License :: OSI Approved :: GNU General Public License v3 or later (GPLv3+)
Classifier: Operating System :: OS Independent
Requires-Python: >=3.9
License-File: LICENSE
Requires-Dist: inotify
Requires-Dist: psutil
Requires-Dist: pyaml
Requires-Dist: python-dateutil
Requires-Dist: requests
Requires-Dist: filetype
Requires-Dist: skilleter-modules
Dynamic: license-file
